[{
    "context": "http://schema.org",
        "type": "Restaurant",
        "name": "BOM APPETITE",
        "image" : "https://d1jgln4w9al398.cloudfront.net/imagens/ce/logosgde/201712020931_f482aa19-ca79-4554-b594-bd3fa3f7609b.png",
        "priceRange": "$",
        "servesCuisine": "Comida Brasileira",
        "url": "https://www.ifood.com.br/delivery/indaiatuba-sp/bom-appetite-jardim-sao-francisco",
        "address": {
            "addresstype": "PostalAddress",
            "addressLocality": "INDAIATUBA",
            "addressRegion": "SP",
            "addressCountry": "BR"
            }
    }
,
    {
    "context": "http://schema.org",
        "type": "Restaurant",
        "name": "Tempero Mania",
        "image" : "https://d1jgln4w9al398.cloudfront.net/imagens/ce/logosgde/201711070924_d7e9bb3c-1269-484f-93cf-ec14a10b56d8.png",
        "priceRange": "$",
        "servesCuisine": "Cozinha Rápida",
        "url": "https://www.ifood.com.br/delivery/indaiatuba-sp/tempero-mania-jardim-morada-do-sol",
        "address": {
            "addresstype": "PostalAddress",
            "addressLocality": "INDAIATUBA",
            "addressRegion": "SP",
            "addressCountry": "BR"
            }
    }
,
    {
    "context": "http://schema.org",
        "type": "Restaurant",
        "name": "Saladenha",
        "image" : "https://d1jgln4w9al398.cloudfront.net/imagens/ce/logosgde/logo (4)_saladenha.png",
        "priceRange": "$",
        "servesCuisine": "Comida Saudável",
        "url": "https://www.ifood.com.br/delivery/indaiatuba-sp/saladenha-cidade-nova-i",
        "address": {
            "addresstype": "PostalAddress",
            "addressLocality": "INDAIATUBA",
            "addressRegion": "SP",
            "addressCountry": "BR"
            }
    }
,
    {
    "context": "http://schema.org",
        "type": "Restaurant",
        "name": "INOUE SUSHI",
        "image" : "https://d1jgln4w9al398.cloudfront.net/imagens/ce/logosgde/201706121303_7d7844d5-8083-41e2-b349-1f4f31a41b65.jpg",
        "priceRange": "$",
        "servesCuisine": "Comida Japonesa",
        "url": "https://www.ifood.com.br/delivery/indaiatuba-sp/inoue-sushi-vila-almeida",
        "address": {
            "addresstype": "PostalAddress",
            "addressLocality": "INDAIATUBA",
            "addressRegion": "SP",
            "addressCountry": "BR"
            }
    }
,
    {
    "context": "http://schema.org",
        "type": "Restaurant",
        "name": "Kare Gyudon",
        "image" : "https://d1jgln4w9al398.cloudfront.net/imagens/ce/logosgde/201702160933_KAREGYUDON.png",
        "priceRange": "$",
        "servesCuisine": "Comida Japonesa",
        "url": "https://www.ifood.com.br/delivery/indaiatuba-sp/kare-gyudon-jardim-esplanada",
        "address": {
            "addresstype": "PostalAddress",
            "addressLocality": "INDAIATUBA",
            "addressRegion": "SP",
            "addressCountry": "BR"
            }
    }
,
    {
    "context": "http://schema.org",
        "type": "Restaurant",
        "name": "Fit Burgers - Indaiatuba",
        "image" : "https://d1jgln4w9al398.cloudfront.net/imagens/ce/logosgde/89046c1b-15f1-49a7-9930-1328d99927e2/201712152041_logof.png",
        "priceRange": "$$",
        "servesCuisine": "Lanches",
        "url": "https://www.ifood.com.br/delivery/indaiatuba-sp/fit-burgers---indaiatuba-cidade-nova-i",
        "address": {
            "addresstype": "PostalAddress",
            "addressLocality": "INDAIATUBA",
            "addressRegion": "SP",
            "addressCountry": "BR"
            }
    }
,
    {
    "context": "http://schema.org",
        "type": "Restaurant",
        "name": "Tio Rô Mini Salgados",
        "image" : "https://d1jgln4w9al398.cloudfront.net/imagens/ce/logosgde/201707071451_c59d3fce-7c21-4c5b-a8af-7f6b32053562.png",
        "priceRange": "$",
        "servesCuisine": "Comida Variada",
        "url": "https://www.ifood.com.br/delivery/indaiatuba-sp/tio-ro-mini-salgados-cidade-nova-i",
        "address": {
            "addresstype": "PostalAddress",
            "addressLocality": "INDAIATUBA",
            "addressRegion": "SP",
            "addressCountry": "BR"
            }
    }
,
    {
    "context": "http://schema.org",
        "type": "Restaurant",
        "name": "REI DO SABOR RESTAURANTE",
        "image" : "https://d1jgln4w9al398.cloudfront.net/imagens/ce/logosgde/201708221051_8879a484-c5de-4e2a-bc4e-d7ee756ef266.jpg",
        "priceRange": "$",
        "servesCuisine": "Comida Brasileira",
        "url": "https://www.ifood.com.br/delivery/indaiatuba-sp/rei-do-sabor-restaurante-centro",
        "address": {
            "addresstype": "PostalAddress",
            "addressLocality": "INDAIATUBA",
            "addressRegion": "SP",
            "addressCountry": "BR"
            }
    }
,
    {
    "context": "http://schema.org",
        "type": "Restaurant",
        "name": "Rota 21",
        "image" : "https://d1jgln4w9al398.cloudfront.net/imagens/ce/logosgde/201706271541_0f89d5a9-ce4e-492f-93b2-bdba478b3193.jpg",
        "priceRange": "$",
        "servesCuisine": "Comida Brasileira",
        "url": "https://www.ifood.com.br/delivery/indaiatuba-sp/rota-21-jardim-morada-do-sol",
        "address": {
            "addresstype": "PostalAddress",
            "addressLocality": "INDAIATUBA",
            "addressRegion": "SP",
            "addressCountry": "BR"
            }
    }
,
    {
    "context": "http://schema.org",
        "type": "Restaurant",
        "name": "Rei do Salgado",
        "image" : "https://d1jgln4w9al398.cloudfront.net/imagens/ce/logosgde/201711091203_6e8a10f4-873c-436a-8406-9824dcd11571.PNG",
        "priceRange": "$$",
        "servesCuisine": "Salgados",
        "url": "https://www.ifood.com.br/delivery/indaiatuba-sp/rei-do-salgado-jardim-california",
        "address": {
            "addresstype": "PostalAddress",
            "addressLocality": "INDAIATUBA",
            "addressRegion": "SP",
            "addressCountry": "BR"
            }
    }
,
    {
    "context": "http://schema.org",
        "type": "Restaurant",
        "name": "Açaí Tropical",
        "image" : "https://d1jgln4w9al398.cloudfront.net/imagens/ce/logosgde/201710160934_850ff321-9460-4ca6-8422-9fc83c4641cb.png",
        "priceRange": "$",
        "servesCuisine": "Comida Brasileira",
        "url": "https://www.ifood.com.br/delivery/indaiatuba-sp/acai-tropical-jardim-remulo-zoppi",
        "address": {
            "addresstype": "PostalAddress",
            "addressLocality": "INDAIATUBA",
            "addressRegion": "SP",
            "addressCountry": "BR"
            }
    }
,
    {
    "context": "http://schema.org",
        "type": "Restaurant",
        "name": "KR Açaiteria",
        "image" : "https://d1jgln4w9al398.cloudfront.net/imagens/ce/logosgde/Açaiteria._DISKC_ATUBAjpeg",
        "priceRange": "$",
        "servesCuisine": "Comida Brasileira",
        "url": "https://www.ifood.com.br/delivery/indaiatuba-sp/kr-acaiteria-jardim-morada-do-sol",
        "address": {
            "addresstype": "PostalAddress",
            "addressLocality": "INDAIATUBA",
            "addressRegion": "SP",
            "addressCountry": "BR"
            }
    }
,
    {
    "context": "http://schema.org",
        "type": "Restaurant",
        "name": "Sushibar Temakeria",
        "image" : "https://d1jgln4w9al398.cloudfront.net/imagens/ce/logosgde/sushibar_sushi_keri02.png",
        "priceRange": "$",
        "servesCuisine": "Comida Japonesa",
        "url": "https://www.ifood.com.br/delivery/indaiatuba-sp/sushibar-temakeria-cidade-nova-i",
        "address": {
            "addresstype": "PostalAddress",
            "addressLocality": "INDAIATUBA",
            "addressRegion": "SP",
            "addressCountry": "BR"
            }
    }
,
    {
    "context": "http://schema.org",
        "type": "Restaurant",
        "name": "China In Box - Indaiatuba",
        "image" : "https://d1jgln4w9al398.cloudfront.net/imagens/ce/logosgde/201708181643_a71b4c1e-ab8b-4831-89a3-d7769950870a.bmp",
        "priceRange": "$$$",
        "servesCuisine": "Comida Chinesa",
        "url": "https://www.ifood.com.br/delivery/indaiatuba-sp/china-in-box---indaiatuba-cidade-nova-i",
        "address": {
            "addresstype": "PostalAddress",
            "addressLocality": "INDAIATUBA",
            "addressRegion": "SP",
            "addressCountry": "BR"
            }
    }
,
    {
    "context": "http://schema.org",
        "type": "Restaurant",
        "name": "Amo Pastel",
        "image" : "https://d1jgln4w9al398.cloudfront.net/imagens/ce/logosgde/amo_pastel_if_AMOPASTEL.jpg",
        "priceRange": "$",
        "servesCuisine": "Lanches",
        "url": "https://www.ifood.com.br/delivery/indaiatuba-sp/amo-pastel-cidade-nova-i",
        "address": {
            "addresstype": "PostalAddress",
            "addressLocality": "INDAIATUBA",
            "addressRegion": "SP",
            "addressCountry": "BR"
            }
    }
,
    {
    "context": "http://schema.org",
        "type": "Restaurant",
        "name": "BAR 644 RESTAURANTE",
        "image" : "https://d1jgln4w9al398.cloudfront.net/imagens/ce/logosgde/201711030908_ea86cf35-76dc-4187-a720-747faa32986d.png",
        "priceRange": "$",
        "servesCuisine": "Comida Brasileira",
        "url": "https://www.ifood.com.br/delivery/indaiatuba-sp/bar-644-restaurante-jardim-portal-de-itaici",
        "address": {
            "addresstype": "PostalAddress",
            "addressLocality": "INDAIATUBA",
            "addressRegion": "SP",
            "addressCountry": "BR"
            }
    }
,
    {
    "context": "http://schema.org",
        "type": "Restaurant",
        "name": "Baguet´s Food",
        "image" : "https://d1jgln4w9al398.cloudfront.net/imagens/ce/logosgde/201711200801_3c51ee0b-a431-4d7b-856b-5813625501ea.jpg",
        "priceRange": "$",
        "servesCuisine": "Lanches",
        "url": "https://www.ifood.com.br/delivery/indaiatuba-sp/baguets-food-vila-costa-e-silva",
        "address": {
            "addresstype": "PostalAddress",
            "addressLocality": "INDAIATUBA",
            "addressRegion": "SP",
            "addressCountry": "BR"
            }
    }
,
    {
    "context": "http://schema.org",
        "type": "Restaurant",
        "name": "Big Pizza",
        "image" : "https://d1jgln4w9al398.cloudfront.net/imagens/ce/logosgde/201710311939_43166fcc-120d-44ca-b3ec-1d3ddf8e8721.png",
        "priceRange": "$",
        "servesCuisine": "Pizza",
        "url": "https://www.ifood.com.br/delivery/indaiatuba-sp/big-pizza-jardim-morada-do-sol",
        "address": {
            "addresstype": "PostalAddress",
            "addressLocality": "INDAIATUBA",
            "addressRegion": "SP",
            "addressCountry": "BR"
            }
    }
,
    {
    "context": "http://schema.org",
        "type": "Restaurant",
        "name": "COXINHAS DO COQUINHO INDAIATUBA",
        "image" : "https://d1jgln4w9al398.cloudfront.net/imagens/ce/logosgde/201712010942_f9736ecb-8239-48cd-9823-9b94fdba5837.png",
        "priceRange": "$",
        "servesCuisine": "Salgados",
        "url": "https://www.ifood.com.br/delivery/indaiatuba-sp/coxinhas-do-coquinho-indaiatuba-vila-vitoria-ii",
        "address": {
            "addresstype": "PostalAddress",
            "addressLocality": "INDAIATUBA",
            "addressRegion": "SP",
            "addressCountry": "BR"
            }
    }
,
    {
    "context": "http://schema.org",
        "type": "Restaurant",
        "name": "Croasonho Indaiatuba",
        "image" : "https://d1jgln4w9al398.cloudfront.net/imagens/ce/logosgde/croasonho_CROAS_ATUBA.PNG",
        "priceRange": "$$$",
        "servesCuisine": "Cozinha Rápida",
        "url": "https://www.ifood.com.br/delivery/indaiatuba-sp/croasonho-indaiatuba-cidade-nova-i",
        "address": {
            "addresstype": "PostalAddress",
            "addressLocality": "INDAIATUBA",
            "addressRegion": "SP",
            "addressCountry": "BR"
            }
    }
,
    {
    "context": "http://schema.org",
        "type": "Restaurant",
        "name": "Don Giovanni Pizzaria",
        "image" : "https://d1jgln4w9al398.cloudfront.net/imagens/ce/logosgde/201712081018_a39b88a2-a43c-4859-837e-66ea8d53b738.png",
        "priceRange": "$",
        "servesCuisine": "Pizza",
        "url": "https://www.ifood.com.br/delivery/indaiatuba-sp/don-giovanni-pizzaria-jardim-hubert",
        "address": {
            "addresstype": "PostalAddress",
            "addressLocality": "INDAIATUBA",
            "addressRegion": "SP",
            "addressCountry": "BR"
            }
    }
,
    {
    "context": "http://schema.org",
        "type": "Restaurant",
        "name": "Macarrão na Chapa",
        "image" : "https://d1jgln4w9al398.cloudfront.net/imagens/ce/logosgde/201711030921_2768bab6-a8e3-4c89-ae81-0a1ad1e819fc.png",
        "priceRange": "$",
        "servesCuisine": "Comida Variada",
        "url": "https://www.ifood.com.br/delivery/indaiatuba-sp/macarrao-na-chapa-jardim-belo-horizonte",
        "address": {
            "addresstype": "PostalAddress",
            "addressLocality": "INDAIATUBA",
            "addressRegion": "SP",
            "addressCountry": "BR"
            }
    }
,
    {
    "context": "http://schema.org",
        "type": "Restaurant",
        "name": "Mr. Burguer",
        "image" : "https://d1jgln4w9al398.cloudfront.net/imagens/ce/logosgde/201711251246_5183a843-5b94-4de6-984c-32c80df7d80b.png",
        "priceRange": "$",
        "servesCuisine": "Lanches",
        "url": "https://www.ifood.com.br/delivery/indaiatuba-sp/mr-burguer-jardim-residencial-veneza",
        "address": {
            "addresstype": "PostalAddress",
            "addressLocality": "INDAIATUBA",
            "addressRegion": "SP",
            "addressCountry": "BR"
            }
    }
,
    {
    "context": "http://schema.org",
        "type": "Restaurant",
        "name": "MÁGIC LANCHE DO TITA",
        "image" : "https://d1jgln4w9al398.cloudfront.net/imagens/ce/logosgde/201711061558_630cb5b7-dbb7-4362-9082-2d8abf32e8b7.png",
        "priceRange": "$",
        "servesCuisine": "Lanches",
        "url": "https://www.ifood.com.br/delivery/indaiatuba-sp/magic-lanche-do-tita-jardim-adriana",
        "address": {
            "addresstype": "PostalAddress",
            "addressLocality": "INDAIATUBA",
            "addressRegion": "SP",
            "addressCountry": "BR"
            }
    }
,
    {
    "context": "http://schema.org",
        "type": "Restaurant",
        "name": "O ESCRITÓRIO FOOD TRUCK",
        "image" : "https://d1jgln4w9al398.cloudfront.net/imagens/ce/logosgde/201712181358_9ec0f7d0-7587-4e61-b37a-1b4d86543ef0.jpg",
        "priceRange": "$",
        "servesCuisine": "Lanches",
        "url": "https://www.ifood.com.br/delivery/indaiatuba-sp/o-escritorio-food-truck-jardim-adriana",
        "address": {
            "addresstype": "PostalAddress",
            "addressLocality": "INDAIATUBA",
            "addressRegion": "SP",
            "addressCountry": "BR"
            }
    }
,
    {
    "context": "http://schema.org",
        "type": "Restaurant",
        "name": "O Siri Cascudo Lanches",
        "image" : "https://d1jgln4w9al398.cloudfront.net/imagens/ce/logosgde/201712210728_2111466b-2873-48b8-85cf-b972be20890f.png",
        "priceRange": "$",
        "servesCuisine": "Lanches",
        "url": "https://www.ifood.com.br/delivery/indaiatuba-sp/o-siri-cascudo-lanches-jardim-uniao",
        "address": {
            "addresstype": "PostalAddress",
            "addressLocality": "INDAIATUBA",
            "addressRegion": "SP",
            "addressCountry": "BR"
            }
    }
,
    {
    "context": "http://schema.org",
        "type": "Restaurant",
        "name": "PABLO'S CHOPPS BAR",
        "image" : "https://d1jgln4w9al398.cloudfront.net/imagens/ce/logosgde/201711211306_2d43567a-62db-4fc4-b57a-819a4bb66dee.png",
        "priceRange": "$$$",
        "servesCuisine": "Comida Variada",
        "url": "https://www.ifood.com.br/delivery/indaiatuba-sp/pablos-chopps-bar-cidade-nova-i",
        "address": {
            "addresstype": "PostalAddress",
            "addressLocality": "INDAIATUBA",
            "addressRegion": "SP",
            "addressCountry": "BR"
            }
    }
,
    {
    "context": "http://schema.org",
        "type": "Restaurant",
        "name": "Pizzaria Indaiá",
        "image" : "https://d1jgln4w9al398.cloudfront.net/imagens/ce/logosgde/201711240930_b31c5d63-780a-486a-998e-04c5ae549e28.png",
        "priceRange": "$$",
        "servesCuisine": "Pizza",
        "url": "https://www.ifood.com.br/delivery/indaiatuba-sp/pizzaria-indaia-chacara-belvedere",
        "address": {
            "addresstype": "PostalAddress",
            "addressLocality": "INDAIATUBA",
            "addressRegion": "SP",
            "addressCountry": "BR"
            }
    }
,
    {
    "context": "http://schema.org",
        "type": "Restaurant",
        "name": "Pizzaria Presidente",
        "image" : "https://d1jgln4w9al398.cloudfront.net/imagens/ce/logosgde/201712121609_1929853b-3ad6-45ac-a619-125919c03c78.png",
        "priceRange": "$",
        "servesCuisine": "Pizza",
        "url": "https://www.ifood.com.br/delivery/indaiatuba-sp/pizzaria-presidente-jardim-santa-cruz",
        "address": {
            "addresstype": "PostalAddress",
            "addressLocality": "INDAIATUBA",
            "addressRegion": "SP",
            "addressCountry": "BR"
            }
    }
,
    {
    "context": "http://schema.org",
        "type": "Restaurant",
        "name": "Rei do Salgado",
        "image" : "https://d1jgln4w9al398.cloudfront.net/imagens/ce/logosgde/201711141951_48e06cab-b0e3-4884-9f2b-9bb9f471f7ee.png",
        "priceRange": "$",
        "servesCuisine": "Salgados",
        "url": "https://www.ifood.com.br/delivery/indaiatuba-sp/rei-do-salgado-jardim-morada-do-sol",
        "address": {
            "addresstype": "PostalAddress",
            "addressLocality": "INDAIATUBA",
            "addressRegion": "SP",
            "addressCountry": "BR"
            }
    },
 {
    "context": "http://schema.org",
        "type": "Restaurant",
        "name": "Shekina Pizzeria e Esfiharia",
        "image" : "https://d1jgln4w9al398.cloudfront.net/imagens/ce/logosgde/201711281110_d28a916a-04b5-4f42-b7ea-ef62df51089c.jpg",
        "priceRange": "$",
        "servesCuisine": "Pizza",
        "url": "https://www.ifood.com.br/delivery/indaiatuba-sp/shekina-pizzeria-e-esfiharia-nucleo-habitacional-brigadeiro-faria-lima",
        "address": {
            "addresstype": "PostalAddress",
            "addressLocality": "INDAIATUBA",
            "addressRegion": "SP",
            "addressCountry": "BR"
            }
    }
,
    {
    "context": "http://schema.org",
        "type": "Restaurant",
        "name": "Stagione Pizzaria",
        "image" : "https://d1jgln4w9al398.cloudfront.net/imagens/ce/logosgde/201711171010_dd239042-4137-435c-8eab-937d5c53cc36.png",
        "priceRange": "$$",
        "servesCuisine": "Comida Brasileira",
        "url": "https://www.ifood.com.br/delivery/indaiatuba-sp/stagione-pizzaria-vila-vitoria-i",
        "address": {
            "addresstype": "PostalAddress",
            "addressLocality": "INDAIATUBA",
            "addressRegion": "SP",
            "addressCountry": "BR"
            }
    }
,
    {
    "context": "http://schema.org",
        "type": "Restaurant",
        "name": "Torteria do Roque",
        "image" : "https://d1jgln4w9al398.cloudfront.net/imagens/ce/logosgde/201712220809_d7851da5-6ff7-4e0e-b555-d95b7db0c9a7.jpg",
        "priceRange": "$",
        "servesCuisine": "Salgados",
        "url": "https://www.ifood.com.br/delivery/indaiatuba-sp/torteria-do-roque-cidade-nova-i",
        "address": {
            "addresstype": "PostalAddress",
            "addressLocality": "INDAIATUBA",
            "addressRegion": "SP",
            "addressCountry": "BR"
            }
    }
,
    {
    "context": "http://schema.org",
        "type": "Restaurant",
        "name": "Cia Do Salgado",
        "image" : "https://d1jgln4w9al398.cloudfront.net/imagens/ce/logosgde/201708291033_3fc1d6cf-87bb-4ebc-b1b9-6a526bd4a929.png",
        "priceRange": "$",
        "servesCuisine": "Cozinha Rápida",
        "url": "https://www.ifood.com.br/delivery/indaiatuba-sp/cia-do-salgado-vila-brizzola",
        "address": {
            "addresstype": "PostalAddress",
            "addressLocality": "INDAIATUBA",
            "addressRegion": "SP",
            "addressCountry": "BR"
            }
    }
,
    {
    "context": "http://schema.org",
        "type": "Restaurant",
        "name": "Pastéis Cantinho Nobre",
        "image" : "https://d1jgln4w9al398.cloudfront.net/imagens/ce/logosgde/logotipo_canti_atuba.png",
        "priceRange": "$$$",
        "servesCuisine": "Cozinha Rápida",
        "url": "https://www.ifood.com.br/delivery/indaiatuba-sp/pasteis-cantinho-nobre-cidade-nova-i",
        "address": {
            "addresstype": "PostalAddress",
            "addressLocality": "INDAIATUBA",
            "addressRegion": "SP",
            "addressCountry": "BR"
            }
    }
,
    {
    "context": "http://schema.org",
        "type": "Restaurant",
        "name": "Restaurante Barnabé",
        "image" : "https://d1jgln4w9al398.cloudfront.net/imagens/ce/logosgde/201701271051_RESTA_RNABE.png",
        "priceRange": "$$",
        "servesCuisine": "Comida Brasileira",
        "url": "https://www.ifood.com.br/delivery/indaiatuba-sp/restaurante-barnabe-centro",
        "address": {
            "addresstype": "PostalAddress",
            "addressLocality": "INDAIATUBA",
            "addressRegion": "SP",
            "addressCountry": "BR"
            }
    }
,
    {
    "context": "http://schema.org",
        "type": "Restaurant",
        "name": "Pastéis Cantinho Nobre MDS",
        "image" : "https://d1jgln4w9al398.cloudfront.net/imagens/ce/logosgde/capturar_canti_nobre.png",
        "priceRange": "$$",
        "servesCuisine": "Salgados",
        "url": "https://www.ifood.com.br/delivery/indaiatuba-sp/pasteis-cantinho-nobre-mds-jardim-morada-do-sol",
        "address": {
            "addresstype": "PostalAddress",
            "addressLocality": "INDAIATUBA",
            "addressRegion": "SP",
            "addressCountry": "BR"
            }
    }
,
    {
    "context": "http://schema.org",
        "type": "Restaurant",
        "name": "Disk Yakissoba",
        "image" : "https://d1jgln4w9al398.cloudfront.net/imagens/ce/logosgde/201703280951_315f2e278aa34c9ab7f2d5a4d5f97f03.png",
        "priceRange": "$",
        "servesCuisine": "Comida Chinesa",
        "url": "https://www.ifood.com.br/delivery/indaiatuba-sp/disk-yakissoba-residencial-monte-verde",
        "address": {
            "addresstype": "PostalAddress",
            "addressLocality": "INDAIATUBA",
            "addressRegion": "SP",
            "addressCountry": "BR"
            }
    }
,
    {
    "context": "http://schema.org",
        "type": "Restaurant",
        "name": "Pizzaria Styve",
        "image" : "https://d1jgln4w9al398.cloudfront.net/imagens/ce/logosgde/201704201348_024e0c17-ee15-4da9-84f7-999589196e0e.jpg",
        "priceRange": "$$$",
        "servesCuisine": "Comida Brasileira",
        "url": "https://www.ifood.com.br/delivery/indaiatuba-sp/pizzaria-styve-vila-brizzola",
        "address": {
            "addresstype": "PostalAddress",
            "addressLocality": "INDAIATUBA",
            "addressRegion": "SP",
            "addressCountry": "BR"
            }
    }
,
    {
    "context": "http://schema.org",
        "type": "Restaurant",
        "name": "DI POTI STROGONOFF",
        "image" : "https://d1jgln4w9al398.cloudfront.net/imagens/ce/logosgde/201708220859_3f0deb9e-4535-4b66-a8e9-0777d9749c15.png",
        "priceRange": "$",
        "servesCuisine": "Cozinha Rápida",
        "url": "https://www.ifood.com.br/delivery/indaiatuba-sp/di-poti-strogonoff-cidade-nova-i",
        "address": {
            "addresstype": "PostalAddress",
            "addressLocality": "INDAIATUBA",
            "addressRegion": "SP",
            "addressCountry": "BR"
            }
    }
,
    {
    "context": "http://schema.org",
        "type": "Restaurant",
        "name": "D´Sapori",
        "image" : "https://d1jgln4w9al398.cloudfront.net/imagens/ce/logosgde/logo d'sapore_dsapori.jpg",
        "priceRange": "$",
        "servesCuisine": "Comida Variada",
        "url": "https://www.ifood.com.br/delivery/indaiatuba-sp/dsapori-centro",
        "address": {
            "addresstype": "PostalAddress",
            "addressLocality": "INDAIATUBA",
            "addressRegion": "SP",
            "addressCountry": "BR"
            }
    }
,
    {
    "context": "http://schema.org",
        "type": "Restaurant",
        "name": "Uow The Best Burger",
        "image" : "https://d1jgln4w9al398.cloudfront.net/imagens/ce/logosgde/201707081514_1a234710-aadb-4d58-ad13-b05d4be1450e.png",
        "priceRange": "$$",
        "servesCuisine": "Lanches",
        "url": "https://www.ifood.com.br/delivery/indaiatuba-sp/uow-the-best-burger-casa-bella-bosque-residencial",
        "address": {
            "addresstype": "PostalAddress",
            "addressLocality": "INDAIATUBA",
            "addressRegion": "SP",
            "addressCountry": "BR"
            }
    }
,
    {
    "context": "http://schema.org",
        "type": "Restaurant",
        "name": "Big Show Burguer",
        "image" : "https://d1jgln4w9al398.cloudfront.net/imagens/ce/logosgde/201701170840_BIGSH_RGUER.png",
        "priceRange": "$",
        "servesCuisine": "Lanches",
        "url": "https://www.ifood.com.br/delivery/indaiatuba-sp/big-show-burguer-centro",
        "address": {
            "addresstype": "PostalAddress",
            "addressLocality": "INDAIATUBA",
            "addressRegion": "SP",
            "addressCountry": "BR"
            }
    }
,
    {
    "context": "http://schema.org",
        "type": "Restaurant",
        "name": "Santo Porco",
        "image" : "https://d1jgln4w9al398.cloudfront.net/imagens/ce/logosgde/logomarca san_santoporco.png",
        "priceRange": "$",
        "servesCuisine": "Lanches",
        "url": "https://www.ifood.com.br/delivery/indaiatuba-sp/santo-porco-cidade-nova-i",
        "address": {
            "addresstype": "PostalAddress",
            "addressLocality": "INDAIATUBA",
            "addressRegion": "SP",
            "addressCountry": "BR"
            }
    }
,
    {
    "context": "http://schema.org",
        "type": "Restaurant",
        "name": "PIZZARIA BABBO INDAIATUBA",
        "image" : "https://d1jgln4w9al398.cloudfront.net/imagens/ce/logosgde/201707151103_b2bed791-69d0-4af7-90cf-871d6f7e0bf8.jpg",
        "priceRange": "$$$$",
        "servesCuisine": "Pizza",
        "url": "https://www.ifood.com.br/delivery/indaiatuba-sp/pizzaria-babbo-indaiatuba-vila-vitoria-ii",
        "address": {
            "addresstype": "PostalAddress",
            "addressLocality": "INDAIATUBA",
            "addressRegion": "SP",
            "addressCountry": "BR"
            }
    }
,
    {
    "context": "http://schema.org",
        "type": "Restaurant",
        "name": "Ragazzi Lanches",
        "image" : "https://d1jgln4w9al398.cloudfront.net/imagens/ce/logosgde/201709141025_23ea153b-e406-456e-9083-b5ba277f75ee.PNG",
        "priceRange": "$$$$",
        "servesCuisine": "Lanches",
        "url": "https://www.ifood.com.br/delivery/indaiatuba-sp/ragazzi-lanches-vila-pires-da-cunha",
        "address": {
            "addresstype": "PostalAddress",
            "addressLocality": "INDAIATUBA",
            "addressRegion": "SP",
            "addressCountry": "BR"
            }
    }
,
    {
    "context": "http://schema.org",
        "type": "Restaurant",
        "name": "Zolla Rotisserie",
        "image" : "https://d1jgln4w9al398.cloudfront.net/imagens/ce/logosgde/201711180721_212febe3-3c39-4cda-9e49-987bde8f40fe.png",
        "priceRange": "$",
        "servesCuisine": "Comida Variada",
        "url": "https://www.ifood.com.br/delivery/indaiatuba-sp/zolla-rotisserie-jardim-santa-cruz",
        "address": {
            "addresstype": "PostalAddress",
            "addressLocality": "INDAIATUBA",
            "addressRegion": "SP",
            "addressCountry": "BR"
            }
    }
,
    {
    "context": "http://schema.org",
        "type": "Restaurant",
        "name": "ALOHA FOOD AÇAI",
        "image" : "https://d1jgln4w9al398.cloudfront.net/imagens/ce/logosgde/201709140837_8f9f032c-0736-45f0-8ff8-b41d18453016.png",
        "priceRange": "$$",
        "servesCuisine": "Sorvetes",
        "url": "https://www.ifood.com.br/delivery/indaiatuba-sp/aloha-food-acai-jardim-morada-do-sol",
        "address": {
            "addresstype": "PostalAddress",
            "addressLocality": "INDAIATUBA",
            "addressRegion": "SP",
            "addressCountry": "BR"
            }
    }
,
    {
    "context": "http://schema.org",
        "type": "Restaurant",
        "name": "Frango Frites",
        "image" : "https://d1jgln4w9al398.cloudfront.net/imagens/ce/logosgde/logo-frangofr_frangofrit02.png",
        "priceRange": "$$$",
        "servesCuisine": "Comida Variada",
        "url": "https://www.ifood.com.br/delivery/indaiatuba-sp/frango-frites-cidade-nova-i",
        "address": {
            "addresstype": "PostalAddress",
            "addressLocality": "INDAIATUBA",
            "addressRegion": "SP",
            "addressCountry": "BR"
            }
    }
,
    {
    "context": "http://schema.org",
        "type": "Restaurant",
        "name": "Via Toscana Pizzaria",
        "image" : "https://d1jgln4w9al398.cloudfront.net/imagens/ce/logosgde/201708091434_a5bc0233-13e2-4bd4-9014-016c0a4d6055.jpg",
        "priceRange": "$$",
        "servesCuisine": "Pizza",
        "url": "https://www.ifood.com.br/delivery/indaiatuba-sp/via-toscana-pizzaria-cidade-nova-i",
        "address": {
            "addresstype": "PostalAddress",
            "addressLocality": "INDAIATUBA",
            "addressRegion": "SP",
            "addressCountry": "BR"
            }
    }
,
    {
    "context": "http://schema.org",
        "type": "Restaurant",
        "name": "Açaí Container",
        "image" : "https://d1jgln4w9al398.cloudfront.net/imagens/ce/logosgde/201708301725_be3cea02-3243-4c07-a6c1-ebd4ee318391.png",
        "priceRange": "$",
        "servesCuisine": "Comida Saudável",
        "url": "https://www.ifood.com.br/delivery/indaiatuba-sp/acai-container-residencial-monte-verde",
        "address": {
            "addresstype": "PostalAddress",
            "addressLocality": "INDAIATUBA",
            "addressRegion": "SP",
            "addressCountry": "BR"
            }
    }
,
    {
    "context": "http://schema.org",
        "type": "Restaurant",
        "name": "Bonna Pizza",
        "image" : "https://d1jgln4w9al398.cloudfront.net/imagens/ce/logosgde/201708041653_9d51ad1e-26e5-4707-83d2-d23878ae66bf.png",
        "priceRange": "$",
        "servesCuisine": "Pizza",
        "url": "https://www.ifood.com.br/delivery/indaiatuba-sp/bonna-pizza-jardim-morada-do-sol",
        "address": {
            "addresstype": "PostalAddress",
            "addressLocality": "INDAIATUBA",
            "addressRegion": "SP",
            "addressCountry": "BR"
            }
    }
,
    {
    "context": "http://schema.org",
        "type": "Restaurant",
        "name": "Pizzaria Nova La Conquista",
        "image" : "https://d1jgln4w9al398.cloudfront.net/imagens/ce/logosgde/logo_pizza_uista.png",
        "priceRange": "$$$$",
        "servesCuisine": "Pizza",
        "url": "https://www.ifood.com.br/delivery/indaiatuba-sp/pizzaria-nova-la-conquista-centro",
        "address": {
            "addresstype": "PostalAddress",
            "addressLocality": "INDAIATUBA",
            "addressRegion": "SP",
            "addressCountry": "BR"
            }
    }
,
    {
    "context": "http://schema.org",
        "type": "Restaurant",
        "name": "Delicias Do Açai",
        "image" : "https://d1jgln4w9al398.cloudfront.net/imagens/ce/logosgde/logotipo acai_delic_oaca02.jpg",
        "priceRange": "$$",
        "servesCuisine": "Comida Brasileira",
        "url": "https://www.ifood.com.br/delivery/indaiatuba-sp/delicias-do-acai-cidade-nova-i",
        "address": {
            "addresstype": "PostalAddress",
            "addressLocality": "INDAIATUBA",
            "addressRegion": "SP",
            "addressCountry": "BR"
            }
    }
,
    {
    "context": "http://schema.org",
        "type": "Restaurant",
        "name": "Vall Lanches",
        "image" : "https://d1jgln4w9al398.cloudfront.net/imagens/ce/logosgde/201707281936_9b93d76e-1b31-48f8-bad7-63c7edd82d70.jpg",
        "priceRange": "$",
        "servesCuisine": "Lanches",
        "url": "https://www.ifood.com.br/delivery/indaiatuba-sp/vall-lanches-cidade-nova-i",
        "address": {
            "addresstype": "PostalAddress",
            "addressLocality": "INDAIATUBA",
            "addressRegion": "SP",
            "addressCountry": "BR"
            }
    }
,
    {
    "context": "http://schema.org",
        "type": "Restaurant",
        "name": "Donna Preta Chocolate",
        "image" : "https://d1jgln4w9al398.cloudfront.net/imagens/ce/logosgde/201709270907_03e7a82e-7351-4161-a155-6aa5568fd680.jpg",
        "priceRange": "$",
        "servesCuisine": "Doces",
        "url": "https://www.ifood.com.br/delivery/indaiatuba-sp/donna-preta-chocolate-jardim-morada-do-sol",
        "address": {
            "addresstype": "PostalAddress",
            "addressLocality": "INDAIATUBA",
            "addressRegion": "SP",
            "addressCountry": "BR"
            }
    }
,
    {
    "context": "http://schema.org",
        "type": "Restaurant",
        "name": "Pizzas Great",
        "image" : "https://d1jgln4w9al398.cloudfront.net/imagens/ce/logosgde/201710101030_45cfb003-04c1-44ec-8fdc-3b8ac50aa9b8.jpg",
        "priceRange": "$$$",
        "servesCuisine": "Pizza",
        "url": "https://www.ifood.com.br/delivery/indaiatuba-sp/pizzas-great-chacara-areal",
        "address": {
            "addresstype": "PostalAddress",
            "addressLocality": "INDAIATUBA",
            "addressRegion": "SP",
            "addressCountry": "BR"
            }
    }
,
    {
    "context": "http://schema.org",
        "type": "Restaurant",
        "name": "La Pasta Gialla",
        "image" : "https://d1jgln4w9al398.cloudfront.net/imagens/ce/logosgde/201703271535_95c94e61911f4cf895668b494870a89e.jpg",
        "priceRange": "$",
        "servesCuisine": "Comida Italiana",
        "url": "https://www.ifood.com.br/delivery/indaiatuba-sp/la-pasta-gialla-jardim-pau-preto",
        "address": {
            "addresstype": "PostalAddress",
            "addressLocality": "INDAIATUBA",
            "addressRegion": "SP",
            "addressCountry": "BR"
            }
    }
,
    {
    "context": "http://schema.org",
        "type": "Restaurant",
        "name": "PIZZARIA FIOROTTO",
        "image" : "https://d1jgln4w9al398.cloudfront.net/imagens/ce/logosgde/201707081547_81cadd9e-7a32-4370-bee3-59a0ea8ed0d2.png",
        "priceRange": "$",
        "servesCuisine": "Pizza",
        "url": "https://www.ifood.com.br/delivery/indaiatuba-sp/pizzaria-fiorotto-vila-maria-helena",
        "address": {
            "addresstype": "PostalAddress",
            "addressLocality": "INDAIATUBA",
            "addressRegion": "SP",
            "addressCountry": "BR"
            }
    }
,
    {
    "context": "http://schema.org",
        "type": "Restaurant",
        "name": "Empadaria",
        "image" : "https://d1jgln4w9al398.cloudfront.net/imagens/ce/logosgde/201709221953_28b5df0e-e059-4a38-bd03-4afc573975a9.png",
        "priceRange": "$",
        "servesCuisine": "Cozinha Rápida",
        "url": "https://www.ifood.com.br/delivery/indaiatuba-sp/empadaria-cidade-nova-i",
        "address": {
            "addresstype": "PostalAddress",
            "addressLocality": "INDAIATUBA",
            "addressRegion": "SP",
            "addressCountry": "BR"
            }
    },
{
    "context": "http://schema.org",
        "type": "Restaurant",
        "name": "Barrancas Restaurantes",
        "image" : "https://d1jgln4w9al398.cloudfront.net/imagens/ce/logosgde/201708150821_7cac3b26-d4f3-433c-af2d-4b48d194fec1.png",
        "priceRange": "$",
        "servesCuisine": "Comida Brasileira",
        "url": "https://www.ifood.com.br/delivery/indaiatuba-sp/barrancas-restaurantes-cidade-nova-i",
        "address": {
            "addresstype": "PostalAddress",
            "addressLocality": "INDAIATUBA",
            "addressRegion": "SP",
            "addressCountry": "BR"
            }
    }
,
    {
    "context": "http://schema.org",
        "type": "Restaurant",
        "name": "Alecrim Refeições",
        "image" : "https://d1jgln4w9al398.cloudfront.net/imagens/ce/logosgde/201709050824_12102d91-14cc-4c73-82cd-aef420237e42.png",
        "priceRange": "$",
        "servesCuisine": "Comida Brasileira",
        "url": "https://www.ifood.com.br/delivery/indaiatuba-sp/alecrim-refeicoes-jardim-juliana",
        "address": {
            "addresstype": "PostalAddress",
            "addressLocality": "INDAIATUBA",
            "addressRegion": "SP",
            "addressCountry": "BR"
            }
    }
,
    {
    "context": "http://schema.org",
        "type": "Restaurant",
        "name": "Cozinha da Taty",
        "image" : "https://d1jgln4w9al398.cloudfront.net/imagens/ce/logosgde/201710040822_9bb5a871-f4fc-43fc-a29a-0c52414b32f0.png",
        "priceRange": "$",
        "servesCuisine": "Comida Brasileira",
        "url": "https://www.ifood.com.br/delivery/indaiatuba-sp/cozinha-da-taty-jardim-tancredo-neves",
        "address": {
            "addresstype": "PostalAddress",
            "addressLocality": "INDAIATUBA",
            "addressRegion": "SP",
            "addressCountry": "BR"
            }
    }
,
    {
    "context": "http://schema.org",
        "type": "Restaurant",
        "name": "Santo Parque",
        "image" : "https://d1jgln4w9al398.cloudfront.net/imagens/ce/logosgde/201705250813_acb14716-d606-48ff-bebf-c33cb96de346.jpg",
        "priceRange": "$",
        "servesCuisine": "Comida Variada",
        "url": "https://www.ifood.com.br/delivery/indaiatuba-sp/santo-parque-jardim-europa",
        "address": {
            "addresstype": "PostalAddress",
            "addressLocality": "INDAIATUBA",
            "addressRegion": "SP",
            "addressCountry": "BR"
            }
    }
,
    {
    "context": "http://schema.org",
        "type": "Restaurant",
        "name": "Don Ramon Mexican Bar",
        "image" : "https://d1jgln4w9al398.cloudfront.net/imagens/ce/logosgde/201706080825_ef776012-03e5-4cf3-b106-619fcf6a86d4.jpg",
        "priceRange": "$$",
        "servesCuisine": "Comida Mexicana",
        "url": "https://www.ifood.com.br/delivery/indaiatuba-sp/don-ramon-mexican-bar-cidade-nova-i",
        "address": {
            "addresstype": "PostalAddress",
            "addressLocality": "INDAIATUBA",
            "addressRegion": "SP",
            "addressCountry": "BR"
            }
    }
,
    {
    "context": "http://schema.org",
        "type": "Restaurant",
        "name": "Dona Lina Comida Caseira",
        "image" : "https://d1jgln4w9al398.cloudfront.net/imagens/ce/logosgde/201704301112_544921b6-3da8-4d33-820c-15bf0a453e25.png",
        "priceRange": "$",
        "servesCuisine": "Comida Brasileira",
        "url": "https://www.ifood.com.br/delivery/indaiatuba-sp/dona-lina-comida-caseira-jardim-morumbi",
        "address": {
            "addresstype": "PostalAddress",
            "addressLocality": "INDAIATUBA",
            "addressRegion": "SP",
            "addressCountry": "BR"
            }
    }
,
    {
    "context": "http://schema.org",
        "type": "Restaurant",
        "name": "Shimoda Sushi",
        "image" : "https://d1jgln4w9al398.cloudfront.net/imagens/ce/logosgde/201707311010_28622f63-2c24-47bc-81db-d3836dab8770.jpg",
        "priceRange": "$",
        "servesCuisine": "Comida Japonesa",
        "url": "https://www.ifood.com.br/delivery/indaiatuba-sp/shimoda-sushi-cidade-nova-i",
        "address": {
            "addresstype": "PostalAddress",
            "addressLocality": "INDAIATUBA",
            "addressRegion": "SP",
            "addressCountry": "BR"
            }
    }
,
    {
    "context": "http://schema.org",
        "type": "Restaurant",
        "name": "Borolios Lanches",
        "image" : "https://d1jgln4w9al398.cloudfront.net/imagens/ce/logosgde/logomarca bor_borol_nches.png",
        "priceRange": "$",
        "servesCuisine": "Lanches",
        "url": "https://www.ifood.com.br/delivery/indaiatuba-sp/borolios-lanches-jardim-santa-cruz",
        "address": {
            "addresstype": "PostalAddress",
            "addressLocality": "INDAIATUBA",
            "addressRegion": "SP",
            "addressCountry": "BR"
            }
    }
,
    {
    "context": "http://schema.org",
        "type": "Restaurant",
        "name": "Pizzaria Mister Magoo",
        "image" : "https://d1jgln4w9al398.cloudfront.net/imagens/ce/logosgde/201710200930_a1eb3cdb-84f1-413a-b2e2-507e8f6d671a.png",
        "priceRange": "$$",
        "servesCuisine": "Pizza",
        "url": "https://www.ifood.com.br/delivery/indaiatuba-sp/pizzaria-mister-magoo-jardim-morada-do-sol",
        "address": {
            "addresstype": "PostalAddress",
            "addressLocality": "INDAIATUBA",
            "addressRegion": "SP",
            "addressCountry": "BR"
            }
    }
,
    {
    "context": "http://schema.org",
        "type": "Restaurant",
        "name": "TUKKAS RESTAURANTE, LANCHONETE & PIZARIA",
        "image" : "https://d1jgln4w9al398.cloudfront.net/imagens/ce/logosgde/201709271105_6f52a3b7-a7c7-45e8-b1c0-a88193869611.png",
        "priceRange": "$$",
        "servesCuisine": "Comida Variada",
        "url": "https://www.ifood.com.br/delivery/indaiatuba-sp/tukkas-restaurante-lanchonete--pizaria-cidade-nova-i",
        "address": {
            "addresstype": "PostalAddress",
            "addressLocality": "INDAIATUBA",
            "addressRegion": "SP",
            "addressCountry": "BR"
            }
    }
,
    {
    "context": "http://schema.org",
        "type": "Restaurant",
        "name": "Top Brasil Marmitex",
        "image" : "https://d1jgln4w9al398.cloudfront.net/imagens/ce/logosgde/201709201511_b73ef764-15d3-4ea2-94cb-1b2094352f6b.png",
        "priceRange": "$",
        "servesCuisine": "Comida Brasileira",
        "url": "https://www.ifood.com.br/delivery/indaiatuba-sp/top-brasil-marmitex-jardim-dos-colibris",
        "address": {
            "addresstype": "PostalAddress",
            "addressLocality": "INDAIATUBA",
            "addressRegion": "SP",
            "addressCountry": "BR"
            }
    }
,
    {
    "context": "http://schema.org",
        "type": "Restaurant",
        "name": "Império Sushi Delivery",
        "image" : "https://d1jgln4w9al398.cloudfront.net/imagens/ce/logosgde/imperio_imper_iver02.png",
        "priceRange": "$",
        "servesCuisine": "Comida Japonesa",
        "url": "https://www.ifood.com.br/delivery/indaiatuba-sp/imperio-sushi-delivery-centro",
        "address": {
            "addresstype": "PostalAddress",
            "addressLocality": "INDAIATUBA",
            "addressRegion": "SP",
            "addressCountry": "BR"
            }
    }
,
    {
    "context": "http://schema.org",
        "type": "Restaurant",
        "name": "Lanchão & Cia - Indaiatuba",
        "image" : "https://d1jgln4w9al398.cloudfront.net/imagens/ce/logosgde/logo lanchão_LANCH_ATUBA.jpg",
        "priceRange": "$",
        "servesCuisine": "Lanches",
        "url": "https://www.ifood.com.br/delivery/indaiatuba-sp/lanchao--cia---indaiatuba-cidade-nova-i",
        "address": {
            "addresstype": "PostalAddress",
            "addressLocality": "INDAIATUBA",
            "addressRegion": "SP",
            "addressCountry": "BR"
            }
    }
,
    {
    "context": "http://schema.org",
        "type": "Restaurant",
        "name": "Lug's - Indaiatuba",
        "image" : "https://d1jgln4w9al398.cloudfront.net/imagens/ce/logosgde/201708081059_ac061099-5889-4972-86b8-f9f79d1af518.png",
        "priceRange": "$",
        "servesCuisine": "Comida Brasileira",
        "url": "https://www.ifood.com.br/delivery/indaiatuba-sp/lugs---indaiatuba-jardim-tropical",
        "address": {
            "addresstype": "PostalAddress",
            "addressLocality": "INDAIATUBA",
            "addressRegion": "SP",
            "addressCountry": "BR"
            }
    }
,
    {
    "context": "http://schema.org",
        "type": "Restaurant",
        "name": "Divino Mate",
        "image" : "https://d1jgln4w9al398.cloudfront.net/imagens/ce/logosgde/201710051141_b4e65ead-dffc-42e8-9bb6-75342cdc2836.png",
        "priceRange": "$",
        "servesCuisine": "Cozinha Rápida",
        "url": "https://www.ifood.com.br/delivery/indaiatuba-sp/divino-mate-vila-vitoria-ii",
        "address": {
            "addresstype": "PostalAddress",
            "addressLocality": "INDAIATUBA",
            "addressRegion": "SP",
            "addressCountry": "BR"
            }
    }
,
    {
    "context": "http://schema.org",
        "type": "Restaurant",
        "name": "CASA DO ESCONDIDINHO E CIA",
        "image" : "https://d1jgln4w9al398.cloudfront.net/imagens/ce/logosgde/201706060803_edace51f-5a4f-4170-a3c0-ddcc4d7519a9.png",
        "priceRange": "$",
        "servesCuisine": "Comida Brasileira",
        "url": "https://www.ifood.com.br/delivery/indaiatuba-sp/casa-do-escondidinho-e-cia-vila-vitoria-ii",
        "address": {
            "addresstype": "PostalAddress",
            "addressLocality": "INDAIATUBA",
            "addressRegion": "SP",
            "addressCountry": "BR"
            }
    }
,
    {
    "context": "http://schema.org",
        "type": "Restaurant",
        "name": "Restaurante Carne Assada",
        "image" : "https://d1jgln4w9al398.cloudfront.net/imagens/ce/logosgde/201704081306_1424cd6d627946e3b84e874fcab7616c.png",
        "priceRange": "$",
        "servesCuisine": "Comida Brasileira",
        "url": "https://www.ifood.com.br/delivery/indaiatuba-sp/restaurante-carne-assada-jardim-morada-do-sol",
        "address": {
            "addresstype": "PostalAddress",
            "addressLocality": "INDAIATUBA",
            "addressRegion": "SP",
            "addressCountry": "BR"
            }
    }
,
    {
    "context": "http://schema.org",
        "type": "Restaurant",
        "name": "Cozinha Dona Therezinha",
        "image" : "https://d1jgln4w9al398.cloudfront.net/imagens/ce/logosgde/201707270906_13bec05c-e6d6-4f70-b469-db2798f228cf.png",
        "priceRange": "$",
        "servesCuisine": "Comida Brasileira",
        "url": "https://www.ifood.com.br/delivery/indaiatuba-sp/cozinha-dona-therezinha-jardim-eldorado",
        "address": {
            "addresstype": "PostalAddress",
            "addressLocality": "INDAIATUBA",
            "addressRegion": "SP",
            "addressCountry": "BR"
            }
    }
,
    {
    "context": "http://schema.org",
        "type": "Restaurant",
        "name": "Rock Diner Burgers",
        "image" : "https://d1jgln4w9al398.cloudfront.net/imagens/ce/logosgde/201703281016_f09c461b2da34c9faeabbeb20a1111e7.png",
        "priceRange": "$",
        "servesCuisine": "Lanches",
        "url": "https://www.ifood.com.br/delivery/indaiatuba-sp/rock-diner-burgers-cidade-nova-i",
        "address": {
            "addresstype": "PostalAddress",
            "addressLocality": "INDAIATUBA",
            "addressRegion": "SP",
            "addressCountry": "BR"
            }
    }
,
    {
    "context": "http://schema.org",
        "type": "Restaurant",
        "name": "PIZZARIA SABOR INDAIÁ",
        "image" : "https://d1jgln4w9al398.cloudfront.net/imagens/ce/logosgde/201710231655_c2eb02bc-7ff9-4d01-86f7-ce46d0e7ccc5.jpg",
        "priceRange": "$",
        "servesCuisine": "Pizza",
        "url": "https://www.ifood.com.br/delivery/indaiatuba-sp/pizzaria-sabor-indaia-centro",
        "address": {
            "addresstype": "PostalAddress",
            "addressLocality": "INDAIATUBA",
            "addressRegion": "SP",
            "addressCountry": "BR"
            }
    }
,
    {
    "context": "http://schema.org",
        "type": "Restaurant",
        "name": "Fogão Real",
        "image" : "https://d1jgln4w9al398.cloudfront.net/imagens/ce/logosgde/201711061452_d45bd4bd-0953-4e28-89f0-0262aca8d668.png",
        "priceRange": "$",
        "servesCuisine": "Comida Brasileira",
        "url": "https://www.ifood.com.br/delivery/indaiatuba-sp/fogao-real-jardim-regina",
        "address": {
            "addresstype": "PostalAddress",
            "addressLocality": "INDAIATUBA",
            "addressRegion": "SP",
            "addressCountry": "BR"
            }
    }
,
    {
    "context": "http://schema.org",
        "type": "Restaurant",
        "name": "Espetim Bar",
        "image" : "https://d1jgln4w9al398.cloudfront.net/imagens/ce/logosgde/201704022219_c47e8a7f487d48e388c3f0ac9c347bf0.jpg",
        "priceRange": "$",
        "servesCuisine": "Carnes",
        "url": "https://www.ifood.com.br/delivery/indaiatuba-sp/espetim-bar-cidade-nova-i",
        "address": {
            "addresstype": "PostalAddress",
            "addressLocality": "INDAIATUBA",
            "addressRegion": "SP",
            "addressCountry": "BR"
            }
    }
,
    {
    "context": "http://schema.org",
        "type": "Restaurant",
        "name": "Augustus Marmitaria",
        "image" : "https://d1jgln4w9al398.cloudfront.net/imagens/ce/logosgde/201710212324_3b4cfd72-e15f-4d6c-bfa0-2031bc0fdea0.png",
        "priceRange": "$",
        "servesCuisine": "Comida Saudável",
        "url": "https://www.ifood.com.br/delivery/indaiatuba-sp/augustus-marmitaria-parque-das-nacoes",
        "address": {
            "addresstype": "PostalAddress",
            "addressLocality": "INDAIATUBA",
            "addressRegion": "SP",
            "addressCountry": "BR"
            }
    }
,
    {
    "context": "http://schema.org",
        "type": "Restaurant",
        "name": "Maria coxinha",
        "image" : "https://d1jgln4w9al398.cloudfront.net/imagens/ce/logosgde/201709201716_a1841779-1375-46bc-92f1-c9edc0c628e7.png",
        "priceRange": "$",
        "servesCuisine": "Salgados",
        "url": "https://www.ifood.com.br/delivery/indaiatuba-sp/maria-coxinha-centro",
        "address": {
            "addresstype": "PostalAddress",
            "addressLocality": "INDAIATUBA",
            "addressRegion": "SP",
            "addressCountry": "BR"
            }
    }
,
    {
    "context": "http://schema.org",
        "type": "Restaurant",
        "name": "Pizzaria e Esfiharia Dumont",
        "image" : "https://d1jgln4w9al398.cloudfront.net/imagens/ce/logosgde/201708021228_2739cb88-1db2-4296-9772-57529011e3a2.jpg",
        "priceRange": "$$",
        "servesCuisine": "Pizza",
        "url": "https://www.ifood.com.br/delivery/indaiatuba-sp/pizzaria-e-esfiharia-dumont-jardim-morada-do-sol",
        "address": {
            "addresstype": "PostalAddress",
            "addressLocality": "INDAIATUBA",
            "addressRegion": "SP",
            "addressCountry": "BR"
            }
    }]
